rprogress.py
rprogress-1.0.0.dist-info/METADATA
rprogress-1.0.0.dist-info/WHEEL
rprogress-1.0.0.dist-info/top_level.txt
rprogress-1.0.0.dist-info/RECORD
