Metadata-Version: 2.4
Name: rprogress
Version: 1.0.0
Summary: custom rich progress.
Home-page: https://github.com/GeekRicardo/rprogress
Author: Geek·Ricardo
Author-email: GeekRicardozzZ@gmail.com
Requires-Dist: rich
Dynamic: author
Dynamic: author-email
Dynamic: home-page
Dynamic: requires-dist
Dynamic: summary
